{
  "page_number": 4,
  "narration_text": "Now we'll see some examples of internet-connected devices that might seem unusual at first, but are actually quite interesting. Look at the images on the slide, notice the variety of devices, from internet phones to IP picture frames, and even a device called Tweet-a-watt that monitors energy use. Take a closer look at the images, you'll see a mix of everyday objects and specialized devices, all connected to the internet in some way. I want you to focus on how these devices are all part of a larger trend towards greater connectivity. As we explore these examples, let's think about the implications of this trend, and how it's changing the way we live and interact with technology, which will lead us to our next topic.",
  "word_count": 125,
  "estimated_seconds": 57.7,
  "target_seconds": 60,
  "model_used": "llama-3.3-70b-versatile",
  "blocks_used": 28,
  "has_visual_candidate": true
}